MANIFEST.in
README.txt
setup.cfg
setup.py
PloneTerminal.egg-info/PKG-INFO
PloneTerminal.egg-info/SOURCES.txt
PloneTerminal.egg-info/dependency_links.txt
PloneTerminal.egg-info/entry_points.txt
PloneTerminal.egg-info/not-zip-safe
PloneTerminal.egg-info/top_level.txt
ploneterminal/__init__.py
ploneterminal/configure.zcml
ploneterminal/functional.txt
ploneterminal/index.pt
ploneterminal/sh.py
ploneterminal/tests.py
ploneterminal/statics/favicon.ico
ploneterminal/statics/ploneterminal.js
ploneterminal/statics/jquery.terminal/css/jquery.terminal.css
ploneterminal/statics/jquery.terminal/js/dterm.js
ploneterminal/statics/jquery.terminal/js/jquery-1.5.min.js
ploneterminal/statics/jquery.terminal/js/jquery.terminal-0.3.4.js
ploneterminal/statics/jquery.terminal/js/jquery.terminal-0.3.4.min.js