Metadata-Version: 1.0
Name: PloneTerminal
Version: 0.5
Summary: A Terminal for Plone
Home-page: https://github.com/bearstech/PloneTerminal
Author: Bearstech
Author-email: py@bearstech.com
License: GPL
Keywords: plone terminal
Platform: UNKNOWN
Classifier: Framework :: Plone
Classifier: Intended Audience :: Developers
Classifier: License :: OSI Approved :: GNU General Public License (GPL)
